mkslides/__init__.py
mkslides/__main__.py
mkslides/assets/README.md
mkslides/assets/highlight.js/.git
mkslides/assets/highlight.js/.gitignore
mkslides/assets/highlight.js/DIGESTS.md
mkslides/assets/highlight.js/LICENSE
mkslides/assets/highlight.js/README.md
mkslides/assets/highlight.js/build/LICENSE
mkslides/assets/highlight.js/build/README.md
mkslides/assets/highlight.js/build/es/core.js
mkslides/assets/highlight.js/build/es/core.min.js
mkslides/assets/highlight.js/build/es/highlight.js
mkslides/assets/highlight.js/build/es/highlight.min.js
mkslides/assets/highlight.js/build/es/languages/1c.min.js
mkslides/assets/highlight.js/build/es/languages/abnf.min.js
mkslides/assets/highlight.js/build/es/languages/accesslog.min.js
mkslides/assets/highlight.js/build/es/languages/actionscript.min.js
mkslides/assets/highlight.js/build/es/languages/ada.min.js
mkslides/assets/highlight.js/build/es/languages/angelscript.min.js
mkslides/assets/highlight.js/build/es/languages/apache.min.js
mkslides/assets/highlight.js/build/es/languages/applescript.min.js
mkslides/assets/highlight.js/build/es/languages/arcade.min.js
mkslides/assets/highlight.js/build/es/languages/arduino.min.js
mkslides/assets/highlight.js/build/es/languages/armasm.min.js
mkslides/assets/highlight.js/build/es/languages/asciidoc.min.js
mkslides/assets/highlight.js/build/es/languages/aspectj.min.js
mkslides/assets/highlight.js/build/es/languages/autohotkey.min.js
mkslides/assets/highlight.js/build/es/languages/autoit.min.js
mkslides/assets/highlight.js/build/es/languages/avrasm.min.js
mkslides/assets/highlight.js/build/es/languages/awk.min.js
mkslides/assets/highlight.js/build/es/languages/axapta.min.js
mkslides/assets/highlight.js/build/es/languages/bash.min.js
mkslides/assets/highlight.js/build/es/languages/basic.min.js
mkslides/assets/highlight.js/build/es/languages/bnf.min.js
mkslides/assets/highlight.js/build/es/languages/brainfuck.min.js
mkslides/assets/highlight.js/build/es/languages/c.min.js
mkslides-2.0.15.dist-info/licenses/LICENSES/CC0-1.0.txt
mkslides-2.0.15.dist-info/licenses/LICENSES/LicenseRef-GitHubLogoTerms.txt
mkslides-2.0.15.dist-info/licenses/LICENSES/LicenseRef-PythonSoftwareFoundationLogoTerms.txt
mkslides-2.0.15.dist-info/licenses/LICENSES/MIT.txt
mkslides-2.0.15.dist-info/WHEEL
mkslides-2.0.15.dist-info/entry_points.txt
mkslides-2.0.15.dist-info/METADATA
mkslides-2.0.15.dist-info/RECORD
