Metadata-Version: 2.4
Name: mkslides
Version: 2.0.15
Summary: MkSlides - Slides with Markdown using the power of Reveal.js.
Author: MartenBE
License-Expression: MIT
License-File: LICENSES/CC0-1.0.txt
License-File: LICENSES/LicenseRef-GitHubLogoTerms.txt
License-File: LICENSES/LicenseRef-PythonSoftwareFoundationLogoTerms.txt
License-File: LICENSES/MIT.txt
Requires-Dist: beautifulsoup4>=4.14.2
Requires-Dist: click>=8.3.1
Requires-Dist: emoji>=2.15.0
Requires-Dist: jinja2>=3.1.6
Requires-Dist: jsonschema>=4.25.1
Requires-Dist: livereload>=2.7.1
Requires-Dist: markdown>=3.10
Requires-Dist: natsort>=8.4.0
Requires-Dist: omegaconf>=2.3.0
Requires-Dist: python-frontmatter>=1.1.0
Requires-Dist: pyyaml>=6.0.3
Requires-Dist: rich>=14.2.0
Requires-Dist: treelib>=1.8.0
Requires-Dist: types-beautifulsoup4>=4.12.0.20250516
Requires-Dist: types-markdown>=3.10.0.20251106
Requires-Python: >=3.13
Project-URL: Homepage, https://martenbe.github.io/mkslides
Project-URL: Repository, https://github.com/MartenBE/mkslides
